jsrl_library_common/__init__.py
jsrl_library_common/constants/__init__.py
jsrl_library_common/constants/aws/__init__.py
jsrl_library_common/constants/aws/s3_constants.py
jsrl_library_common/exceptions/__init__.py
jsrl_library_common/exceptions/aws/__init__.py
jsrl_library_common/exceptions/aws/s3_exceptions.py
jsrl_library_common/utils/__init__.py
jsrl_library_common/utils/aws/__init__.py
jsrl_library_common/utils/aws/athena.py
jsrl_library_common/utils/aws/lambda_utils.py
jsrl_library_common/utils/aws/s3.py
jsrl_library_common/utils/aws/sqs.py
jsrl_library_common/utils/aws/sts.py
jsrl_library_common_aws-0.0.1.dist-info/licenses/LICENSE.txt
jsrl_library_common_aws-0.0.1.dist-info/METADATA
jsrl_library_common_aws-0.0.1.dist-info/WHEEL
jsrl_library_common_aws-0.0.1.dist-info/top_level.txt
jsrl_library_common_aws-0.0.1.dist-info/RECORD
