Metadata-Version: 2.4
Name: jsrl-library-common-aws
Version: 0.0.1
Summary: library with resuable components/functions by any backend project
Home-page: 
Download-URL: 
Author: Juan Sebastian Reyes Leyton
Author-email: sebas.reyes2002@hotmail.com
License: Copyright (c) 2025 The Python Packaging Authority
Keywords: jsrl-library-common,jsrl-library-common-aws
Platform: Unix
Classifier: Environment :: Console
Classifier: Intended Audience :: Developers
Classifier: Topic :: Software Development :: Libraries
Classifier: Programming Language :: Python
Classifier: Programming Language :: Python :: 3.13
Classifier: Operating System :: OS Independent
License-File: LICENSE.txt
Requires-Dist: boto3==1.35.80
Requires-Dist: botocore==1.35.80
Requires-Dist: s3transfer==0.10.4
Dynamic: author
Dynamic: author-email
Dynamic: classifier
Dynamic: description
Dynamic: keywords
Dynamic: license
Dynamic: license-file
Dynamic: platform
Dynamic: requires-dist
Dynamic: summary
